MANIFEST.in
README
setup.py
bin/wid
bin/wid-update-mail
whatidid/__init__.py
whatidid/commands.py
whatidid/objects.py
whatidid.egg-info/PKG-INFO
whatidid.egg-info/SOURCES.txt
whatidid.egg-info/dependency_links.txt
whatidid.egg-info/not-zip-safe
whatidid.egg-info/top_level.txt