Metadata-Version: 1.0
Name: whatidid
Version: 1.6.4
Summary: A minimalist command line app for life logging.
Home-page: https://github.com/zachseifts/whatidid
Author: Zach Seifts
Author-email: zach.seifts@gmail.com
License: MIT
Keywords: lifelogging whatidid
Platform: UNKNOWN
Classifier: Development Status :: 3 - Alpha
Classifier: License :: OSI Approved :: MIT License
Classifier: Programming Language :: Python :: 2.7
Classifier: Topic :: Office/Business
